pewter.py
pewter-0.1.0.dist-info/METADATA
pewter-0.1.0.dist-info/WHEEL
pewter-0.1.0.dist-info/RECORD
